{
    "data": [
        {
            "name": "Model Name A",
            "stats": {
                "movement": "5",
                "resistance": "6",
                "power": "7",
                "vitality": "8",
                "save": "9"
            },
            "weapons": [],
            "abilities": []
        },
        {
            "name": "Model Name B",
            "stats": {
                "movement": "5",
                "resistance": "6",
                "power": "7",
                "vitality": "8",
                "save": "9"
            },
            "weapons": [],
            "abilities": []
        },
        {
            "name": "Model Name C",
            "stats": {
                "movement": "5",
                "resistance": "6",
                "power": "7",
                "vitality": "8",
                "save": "9"
            },
            "weapons": [],
            "abilities": []
        }
    ],
    "imgur_url": "https://i.imgur.com/1wHQLo1.png",
    "num_cards": 3,
    "cards_per_row": 10,
    "cards_per_col": 1
}